{
  "equ_type": "kdv",
  "flowmap": {
    "type": "rk45",
    "dt": 1e-4,
    "t_step": 1e-2
  },
  "dataset": {
    "n_traj": 100,
    "n_traj_per_param": 1,
    "traj_len": 500,
    "x_min": 0.0,
    "x_max": 1.0,
    "param_min": -1.0,
    "param_max": 1.0,
    "seed_x": 11,
    "seed_param": 22,
    "train_ratio": 0.8,
    "param_time_dependent": true
  },
  "dictionary": {
    "dim_output": 6,
    "dic_layer_sizes": [16, 16]
  },
  "solver": {
    "n_epochs": 1000,
    "batch_size": 1000,
    "tol": 1e-9,
    "dic_lr": 1e-4,
    "koopman_layer_sizes": [36, 36],
    "koopman_lr": 1e-4
  }
}